MiPC/MiAuth/__main__.py
MiPC/Misskey.py
MiPC/__init__.py
MiPC/exceptions.py
MiPC/http.py
misskey_python-1.3.1.dist-info/METADATA
misskey_python-1.3.1.dist-info/WHEEL
misskey_python-1.3.1.dist-info/licenses/LICENSE
misskey_python-1.3.1.dist-info/RECORD
