Metadata-Version: 2.1
Name: misskey-python
Version: 1.3.1
Summary: (discontinued) misskey api library
Author-Email: sonyakun <amase.cocoa@gmail.com>
License: MIT
Project-URL: Repository, https://github.com/MiPC-Dev/MiPC
Requires-Python: <4.0,>=3.10
Requires-Dist: httpx<1.0.0,>=0.24.1
Requires-Dist: pytest<8.0.0,>=7.3.1
Requires-Dist: websockets<12.0.0,>=11.0.3
Requires-Dist: aiofiles<24.0.0,>=23.1.0
Requires-Dist: colorama<1.0.0,>=0.4.6
Requires-Dist: pytest-cov<5.0.0,>=4.1.0
